{
  "utrecht": {
    "paragraph": {
      "color": {
        "type": "color",
        "value": "{nijmegen.color.grijs.500}"
      },
      "font-family": {
        "value": "{nijmegen.document.font-family}",
        "type": "fontFamilies"
      },
      "font-size": {
        "value": "{nijmegen.typography.font-size.sml}",
        "type": "fontSizes"
      },
      "font-weight": {
        "value": "{nijmegen.document.font-weight}",
        "type": "fontWeights"
      },
      "line-height": {
        "value": "{nijmegen.document.line-height}",
        "type": "lineHeights"
      }
    },
    "paragraph-lead": {
      "color": {
        "type": "color",
        "value": "{nijmegen.color.grijs.500}"
      },
      "font-family": {
        "value": "{nijmegen.document.font-family}",
        "type": "fontFamilies"
      },
      "font-size": {
        "value": "{nijmegen.typography.font-size.md}",
        "type": "fontSizes"
      },
      "font-weight": {
        "value": "{nijmegen.typography.font-weight.semi-bold}",
        "type": "fontWeights"
      },
      "line-height": {
        "value": "{nijmegen.document.line-height}",
        "type": "lineHeights"
      }
    },
    "paragraph-small-print": {
      "color": {
        "type": "color",
        "value": "{nijmegen.color.grijs.500}"
      },
      "font-family": {
        "value": "{nijmegen.document.font-family}",
        "type": "fontFamilies"
      },
      "font-size": {
        "value": "{nijmegen.typography.font-size.sm}",
        "type": "fontSizes"
      },
      "font-weight": {
        "value": "{nijmegen.document.font-weight}",
        "type": "fontWeights"
      },
      "line-height": {
        "value": "{nijmegen.document.line-height}",
        "type": "lineHeights"
      }
    }
  }
}